{
  "image_path": "yearly_bestsellers_2021\\covers\\034_266023721_아버지에게 갔었어_신경숙지은이.jpg",
  "timestamp": "2025-11-12T01:10:03.976223",
  "has_belly_band": false,
  "belly_band": null,
  "all_texts": [
    {
      "text": "아버지에게",
      "confidence": 0.6120279096995965,
      "bbox": [
        [
          321.0,
          35.0
        ],
        [
          465.0,
          35.0
        ],
        [
          465.0,
          73.0
        ],
        [
          321.0,
          73.0
        ]
      ]
    },
    {
      "text": "갖없어",
      "confidence": 0.8363539916353097,
      "bbox": [
        [
          372.0,
          65.0
        ],
        [
          465.0,
          65.0
        ],
        [
          465.0,
          109.0
        ],
        [
          372.0,
          109.0
        ]
      ]
    },
    {
      "text": "신경숙 장필소설",
      "confidence": 0.49471980764188883,
      "bbox": [
        [
          348.0,
          310.0
        ],
        [
          462.0,
          310.0
        ],
        [
          462.0,
          334.0
        ],
        [
          348.0,
          334.0
        ]
      ]
    }
  ],
  "total_text_blocks": 3
}