{
  "image_path": "yearly_bestsellers_2021\\covers\\049_272864870_눈으로 만든 사람_최은미지은이.jpg",
  "timestamp": "2025-11-12T01:10:11.601975",
  "has_belly_band": true,
  "belly_band": {
    "type": "group",
    "text": "올 최은미 소설",
    "confidence": 0.6691341888439503,
    "score": 56.274025665318504,
    "bbox": [
      [
        62.0,
        286.0
      ],
      [
        424.0,
        286.0
      ],
      [
        424.0,
        386.0
      ],
      [
        62.0,
        386.0
      ]
    ],
    "text_count": 3,
    "position": 0.4609053497942387
  },
  "all_texts": [
    {
      "text": "최은미",
      "confidence": 0.6605795923315496,
      "bbox": [
        [
          62.0,
          338.0
        ],
        [
          122.0,
          338.0
        ],
        [
          122.0,
          364.0
        ],
        [
          62.0,
          364.0
        ]
      ]
    },
    {
      "text": "올",
      "confidence": 0.34684438473221135,
      "bbox": [
        [
          396.0,
          286.0
        ],
        [
          424.0,
          286.0
        ],
        [
          424.0,
          380.0
        ],
        [
          396.0,
          380.0
        ]
      ]
    },
    {
      "text": "소설",
      "confidence": 0.9999785894680898,
      "bbox": [
        [
          72.0,
          362.0
        ],
        [
          112.0,
          362.0
        ],
        [
          112.0,
          386.0
        ],
        [
          72.0,
          386.0
        ]
      ]
    },
    {
      "text": "딴",
      "confidence": 0.4067371123624639,
      "bbox": [
        [
          396.0,
          400.0
        ],
        [
          428.0,
          400.0
        ],
        [
          428.0,
          466.0
        ],
        [
          396.0,
          466.0
        ]
      ]
    },
    {
      "text": "참",
      "confidence": 0.23080961258856192,
      "bbox": [
        [
          396.0,
          484.0
        ],
        [
          428.0,
          484.0
        ],
        [
          428.0,
          546.0
        ],
        [
          396.0,
          546.0
        ]
      ]
    },
    {
      "text": "\"당신의 소설이 나름 어떻계 흔들/는지름 말하게 훨까화",
      "confidence": 0.21716635229498732,
      "bbox": [
        [
          50.0,
          590.0
        ],
        [
          454.0,
          590.0
        ],
        [
          454.0,
          616.0
        ],
        [
          50.0,
          616.0
        ]
      ]
    },
    {
      "text": "말할 기회가 영영 없올까화 초조있다 `",
      "confidence": 0.2425782380215696,
      "bbox": [
        [
          74.0,
          614.0
        ],
        [
          340.0,
          614.0
        ],
        [
          340.0,
          640.0
        ],
        [
          74.0,
          640.0
        ]
      ]
    },
    {
      "text": "_항정은소설가)",
      "confidence": 0.3099007434144925,
      "bbox": [
        [
          347.0,
          617.0
        ],
        [
          429.0,
          617.0
        ],
        [
          429.0,
          637.0
        ],
        [
          347.0,
          637.0
        ]
      ]
    },
    {
      "text": "202 현대문회상 수상작 [여기 우리마주 ]",
      "confidence": 0.13448821855957616,
      "bbox": [
        [
          143.0,
          653.0
        ],
        [
          357.0,
          653.0
        ],
        [
          357.0,
          673.0
        ],
        [
          143.0,
          673.0
        ]
      ]
    },
    {
      "text": "2017 접온작가상 수상자 '눈으로 만드 사람,수구",
      "confidence": 0.23332884571050097,
      "bbox": [
        [
          127.0,
          671.0
        ],
        [
          377.0,
          671.0
        ],
        [
          377.0,
          689.0
        ],
        [
          127.0,
          689.0
        ]
      ]
    }
  ],
  "total_text_blocks": 10
}