{
  "image_path": "yearly_bestsellers_2020\\covers\\006_239400216_소년이 온다 특별한정판 양장_한강지은이.jpg",
  "timestamp": "2025-11-12T01:10:39.108305",
  "has_belly_band": true,
  "belly_band": {
    "type": "group",
    "text": "향 숨",
    "confidence": 0.584985577513411,
    "score": 61.129567325402334,
    "bbox": [
      [
        63.0,
        243.0
      ],
      [
        456.0,
        243.0
      ],
      [
        456.0,
        318.0
      ],
      [
        63.0,
        318.0
      ]
    ],
    "text_count": 2,
    "position": 0.3879668049792531
  },
  "all_texts": [
    {
      "text": "향",
      "confidence": 0.25707779931716246,
      "bbox": [
        [
          63.0,
          259.0
        ],
        [
          83.0,
          259.0
        ],
        [
          83.0,
          299.0
        ],
        [
          63.0,
          299.0
        ]
      ]
    },
    {
      "text": "숨",
      "confidence": 0.9128933557096595,
      "bbox": [
        [
          426.0,
          243.0
        ],
        [
          456.0,
          243.0
        ],
        [
          456.0,
          318.0
        ],
        [
          426.0,
          318.0
        ]
      ]
    },
    {
      "text": "줄",
      "confidence": 0.05111889777405865,
      "bbox": [
        [
          65.0,
          303.0
        ],
        [
          81.0,
          303.0
        ],
        [
          81.0,
          365.0
        ],
        [
          65.0,
          365.0
        ]
      ]
    },
    {
      "text": "올",
      "confidence": 0.03363915842852805,
      "bbox": [
        [
          430.0,
          330.0
        ],
        [
          456.0,
          330.0
        ],
        [
          456.0,
          382.0
        ],
        [
          430.0,
          382.0
        ]
      ]
    }
  ],
  "total_text_blocks": 4
}