{
  "image_path": "yearly_bestsellers_2024\\covers\\051_329514317_메리골드 마음 세탁소 30만 부 기념 한정 플라워 에디_윤정은지은이.jpg",
  "timestamp": "2025-11-12T01:07:51.576876",
  "has_belly_band": true,
  "belly_band": {
    "type": "group",
    "text": "2023 교육청 선정 도서 청소년이 선정한 추천 도세 No.1 만부",
    "confidence": 0.9368887599518869,
    "score": 93.84666279855661,
    "bbox": [
      [
        45.0,
        691.0
      ],
      [
        474.0,
        691.0
      ],
      [
        474.0,
        732.0
      ],
      [
        45.0,
        732.0
      ]
    ],
    "text_count": 3,
    "position": 0.9640921409214093
  },
  "all_texts": [
    {
      "text": "\"ttirigoll Ilinid L_tiidi\"?)",
      "confidence": 0.10931260987112246,
      "bbox": [
        [
          147.0,
          70.0
        ],
        [
          359.0,
          70.0
        ],
        [
          359.0,
          101.0
        ],
        [
          147.0,
          101.0
        ]
      ]
    },
    {
      "text": "메리골드 마음세탁소",
      "confidence": 0.6696200887740434,
      "bbox": [
        [
          121.0,
          115.0
        ],
        [
          383.0,
          115.0
        ],
        [
          383.0,
          159.0
        ],
        [
          121.0,
          159.0
        ]
      ]
    },
    {
      "text": "운정은 장편소선",
      "confidence": 0.757006743242525,
      "bbox": [
        [
          209.0,
          173.0
        ],
        [
          299.0,
          173.0
        ],
        [
          299.0,
          193.0
        ],
        [
          209.0,
          193.0
        ]
      ]
    },
    {
      "text": "\"나에계도 마음 세락소가 있다면 좋짓다\"",
      "confidence": 0.3377120515735019,
      "bbox": [
        [
          36.0,
          572.0
        ],
        [
          356.0,
          572.0
        ],
        [
          356.0,
          600.0
        ],
        [
          36.0,
          600.0
        ]
      ]
    },
    {
      "text": "억대급 입소문 누적 판매 30만 부 표파",
      "confidence": 0.32977176395541113,
      "bbox": [
        [
          45.0,
          617.0
        ],
        [
          239.0,
          617.0
        ],
        [
          239.0,
          637.0
        ],
        [
          45.0,
          637.0
        ]
      ]
    },
    {
      "text": "품라위",
      "confidence": 0.7014356508221712,
      "bbox": [
        [
          421.0,
          613.0
        ],
        [
          459.0,
          613.0
        ],
        [
          459.0,
          629.0
        ],
        [
          421.0,
          629.0
        ]
      ]
    },
    {
      "text": "온라인서점 선정 2023 소설 메스트선러1위",
      "confidence": 0.2063944654737838,
      "bbox": [
        [
          45.0,
          635.0
        ],
        [
          259.0,
          635.0
        ],
        [
          259.0,
          655.0
        ],
        [
          45.0,
          655.0
        ]
      ]
    },
    {
      "text": "한국소선 최최 평권괜터하우스 최고가수히",
      "confidence": 0.1497379493739396,
      "bbox": [
        [
          43.0,
          653.0
        ],
        [
          263.0,
          653.0
        ],
        [
          263.0,
          673.0
        ],
        [
          43.0,
          673.0
        ]
      ]
    },
    {
      "text": "전세계 영미권 포합 20개국 계약 진행",
      "confidence": 0.48977472052750404,
      "bbox": [
        [
          45.0,
          671.0
        ],
        [
          237.0,
          671.0
        ],
        [
          237.0,
          691.0
        ],
        [
          45.0,
          691.0
        ]
      ]
    },
    {
      "text": "'23 한국소설",
      "confidence": 0.4868975422159424,
      "bbox": [
        [
          327.0,
          669.0
        ],
        [
          397.0,
          669.0
        ],
        [
          397.0,
          689.0
        ],
        [
          327.0,
          689.0
        ]
      ]
    },
    {
      "text": "30",
      "confidence": 0.9942142746977464,
      "bbox": [
        [
          395.0,
          639.0
        ],
        [
          497.0,
          639.0
        ],
        [
          497.0,
          705.0
        ],
        [
          395.0,
          705.0
        ]
      ]
    },
    {
      "text": "2023 교육청 선정 도서 청소년이 선정한 추천 도세",
      "confidence": 0.813333989192905,
      "bbox": [
        [
          45.0,
          691.0
        ],
        [
          297.0,
          691.0
        ],
        [
          297.0,
          709.0
        ],
        [
          45.0,
          709.0
        ]
      ]
    },
    {
      "text": "No.1",
      "confidence": 0.9973698854446411,
      "bbox": [
        [
          323.0,
          691.0
        ],
        [
          403.0,
          691.0
        ],
        [
          403.0,
          729.0
        ],
        [
          323.0,
          729.0
        ]
      ]
    },
    {
      "text": "만부",
      "confidence": 0.9999624052181145,
      "bbox": [
        [
          420.0,
          700.0
        ],
        [
          474.0,
          700.0
        ],
        [
          474.0,
          732.0
        ],
        [
          420.0,
          732.0
        ]
      ]
    },
    {
      "text": "(에디선",
      "confidence": 0.6389607191085815,
      "bbox": [
        [
          459.4356673520169,
          606.0812689968575
        ],
        [
          499.9924811763914,
          622.8267407672703
        ],
        [
          491.5643326479831,
          643.9187310031425
        ],
        [
          450.0075188236086,
          627.1732592327297
        ]
      ]
    },
    {
      "text": "'한정판",
      "confidence": 0.4442097544670105,
      "bbox": [
        [
          379.28501414857493,
          623.971008489145
        ],
        [
          421.4358007869021,
          610.6077083278525
        ],
        [
          427.71498585142507,
          632.028991510855
        ],
        [
          385.5641992130979,
          645.3922916721475
        ]
      ]
    }
  ],
  "total_text_blocks": 16
}